aisee/__init__.py
aisee/custom_datasets.py
aisee/trainer.py
aisee/utils.py
aisee/vision_classifier.py
aisee-0.1.1.dist-info/LICENSE
aisee-0.1.1.dist-info/METADATA
aisee-0.1.1.dist-info/WHEEL
aisee-0.1.1.dist-info/RECORD
