Metadata-Version: 2.1
Name: aisee
Version: 0.1.1
Summary: aisee is a Python package for image classification using PyTorch and timm created by Instituto de Ingeniería del Conocimiento
Home-page: https://iiconocimiento.github.io/aisee
License: MIT
Keywords: aisee,computer vision,vision,timm,pytorch
Author: IIC
Requires-Python: >=3.9,<3.12
Classifier: Development Status :: 5 - Production/Stable
Classifier: Intended Audience :: Science/Research
Classifier: License :: OSI Approved :: MIT License
Classifier: Operating System :: OS Independent
Classifier: Programming Language :: Python
Classifier: Programming Language :: Python :: 3
Classifier: Programming Language :: Python :: 3.9
Classifier: Programming Language :: Python :: 3.10
Classifier: Programming Language :: Python :: 3.11
Classifier: Programming Language :: Python :: 3 :: Only
Classifier: Topic :: Scientific/Engineering
Requires-Dist: Pillow (>=8.4.0)
Requires-Dist: datasets (>=2)
Requires-Dist: huggingface-hub (>=0.13)
Requires-Dist: pandas (>=1)
Requires-Dist: scikit-learn (>=1)
Requires-Dist: timm (>=0.5.4)
Requires-Dist: torch (>2.2.0)
Requires-Dist: torchvision (>=0.11.3)
Project-URL: Documentation, https://iiconocimiento.github.io/aisee
Project-URL: Repository, https://github.com/iiconocimiento/aisee
